welford_torch/__init__.py
welford_torch/covariance_torch.py
welford_torch/example.py
welford_torch/test_covariance.py
welford_torch/test_welford.py
welford_torch/welford_torch.py
welford_torch-0.2.5.dist-info/LICENSE
welford_torch-0.2.5.dist-info/METADATA
welford_torch-0.2.5.dist-info/WHEEL
welford_torch-0.2.5.dist-info/top_level.txt
welford_torch-0.2.5.dist-info/RECORD
