Metadata-Version: 2.2
Name: welford-torch
Version: 0.2.5
Summary: Online Pytorch implementation to get Standard Deviation, Covariance, Correlation and Whitening.
Home-page: https://github.com/pesvut/welford-torch
Author: Nicky Pochinkov
Author-email: work@nicky.pro
License: MIT
Keywords: statistics,online,welford,torch,covariance,correlation
License-File: LICENSE
Requires-Dist: torch
Requires-Dist: einops
Dynamic: author
Dynamic: author-email
Dynamic: description
Dynamic: description-content-type
Dynamic: home-page
Dynamic: keywords
Dynamic: license
Dynamic: requires-dist
Dynamic: summary
